Metadata-Version: 2.1
Name: MicroPyDD-firestore
Version: 0.0.3
Summary: MicroPyDD wrapper for Google firestore
Home-page: UNKNOWN
Author: Danilo Delizia
Author-email: ddelizia@gmail.com
License: UNKNOWN
Platform: UNKNOWN
